stackoverflow_java_queries/CodeExtractor.py
stackoverflow_java_queries/CodeParser.py
stackoverflow_java_queries/DataCollector.py
stackoverflow_java_queries/__init__.py
stackoverflow_java_queries-0.1.2.dist-info/LICENSE.rtf
stackoverflow_java_queries-0.1.2.dist-info/METADATA
stackoverflow_java_queries-0.1.2.dist-info/WHEEL
stackoverflow_java_queries-0.1.2.dist-info/top_level.txt
stackoverflow_java_queries-0.1.2.dist-info/RECORD
